LICENSE
ecoindex/__init__.py
ecoindex/data/grades.py
ecoindex/data/medians.py
ecoindex/data/quantiles.py
ecoindex/data/targets.py
ecoindex/ecoindex.py
ecoindex/models.py
ecoindex/utils.py
ecoindex-5.4.2.dist-info/LICENSE
ecoindex-5.4.2.dist-info/METADATA
ecoindex-5.4.2.dist-info/WHEEL
ecoindex-5.4.2.dist-info/entry_points.txt
ecoindex-5.4.2.dist-info/RECORD
