Metadata-Version: 2.1
Name: ecoindex
Version: 5.4.2
Summary: Ecoindex module provides a simple way to measure the Ecoindex score based on the 3 parameters: The DOM elements of the page, the size of the page and the number of external requests of the page
Home-page: http://www.ecoindex.fr
License: MIT
Author: Vincent Vatelot
Author-email: vincent.vatelot@ik.me
Requires-Python: >=3.10,<4.0
Classifier: License :: OSI Approved :: MIT License
Classifier: Programming Language :: Python :: 3
Classifier: Programming Language :: Python :: 3.10
Classifier: Programming Language :: Python :: 3.11
Requires-Dist: aiofile (>=3.8.1,<4.0.0)
Requires-Dist: pydantic (>=1.10.2,<2.0.0)
Requires-Dist: requests (>=2.28.2,<3.0.0)
Project-URL: Repository, https://github.com/cnumr/ecoindex_python
